econ_watcher_reader/__init__.py
econ_watcher_reader/parser.py
econ_watcher_reader/reader.py
econ_watcher_reader/scraper.py
econ_watcher_reader/settings.py
econ_watcher_reader-0.0.3.dist-info/METADATA
econ_watcher_reader-0.0.3.dist-info/RECORD
econ_watcher_reader-0.0.3.dist-info/WHEEL
econ_watcher_reader-0.0.3.dist-info/top_level.txt
