Metadata-Version: 2.1
Name: econ-watcher-reader
Version: 0.0.3
Summary: Web scraper to get economy watcher data from Cabinet Office of Japan.
Home-page: https://github.com/si4141/scraper_for_economy_watcher
Author: Yuta Sugiura
Author-email: ced4141@me.com
License: MIT
Platform: UNKNOWN
Classifier: Programming Language :: Python :: 3.7
Classifier: License :: OSI Approved :: MIT License
Classifier: Development Status :: 4 - Beta
Requires-Dist: numpy
Requires-Dist: pandas
Requires-Dist: xlrd
Requires-Dist: requests
Requires-Dist: bs4
